index.py
setup.cfg
setup.py
Alfe.egg-info/PKG-INFO
Alfe.egg-info/SOURCES.txt
Alfe.egg-info/dependency_links.txt
Alfe.egg-info/entry_points.txt
Alfe.egg-info/requires.txt
Alfe.egg-info/top_level.txt
Alfe.egg-info/testfolder/requires.txt