Metadata-Version: 1.0
Name: Alfe
Version: 0.1.0
Summary: Extract TODO comment tags from source files
Home-page: https://github.com/cyluun/alfe
Author: Ada Vasiliu
Author-email: UNKNOWN
License: MIT
Platform: UNKNOWN
